{
    "type": "minecraft:crafting_shapeless",
    "group": "minecraft:fox_spawn_egg",
    "ingredients": [
        {
            "item": "minecraft:egg"
        },
        {
            "item": "minecraft:lapis_lazuli"
        },
        {
            "item": "minecraft:lapis_lazuli"
        },
        {
            "item": "minecraft:lapis_lazuli"
        },
        {
            "item": "minecraft:sweet_berries"
        },
        {
            "item": "minecraft:fern"
        }
    ],
    "result": {
        "item": "minecraft:fox_spawn_egg",
        "count": 1
    }
}
